{
  "resourceType": "MedicationRequest",
  "id": "medicationrequest-001",
  "meta": {
    "profile": [
      "http://hl7.org/fhir/us/core/StructureDefinition/us-core-medicationrequest"
    ]
  },
  "status": "active",
  "intent": "order",
  "medicationCodeableConcept": {
    "coding": [
      { "system": "http://www.nlm.nih.gov/research/umls/rxnorm", "code": "1049630", "display": "Gabapentin 300 MG Oral Capsule" }
    ]
  },
  "subject": { "reference": "Patient/patient-001" },
  "encounter": { "reference": "Encounter/encounter-001" },
  "authoredOn": "2026-05-18",
  "requester": { "reference": "Practitioner/practitioner-001" },
  "dosageInstruction": [
    {
      "text": "Take 1 capsule by mouth three times daily.",
      "timing": {
        "repeat": { "frequency": 3, "period": 1, "periodUnit": "d" }
      },
      "route": {
        "coding": [
          { "system": "http://snomed.info/sct", "code": "26643006", "display": "Oral route" }
        ]
      }
    }
  ]
}
